[
  {"name": "a", "file": "example-001-a.html"},
  {"name": "abbr", "file": "example-002-abbr.html"},
  {"name": "b", "file": "example-003-b.html"},
  {"name": "bdi", "file": "example-004-bdi.html"},
  {"name": "bdo", "file": "example-005-bdo.html"},
  {"name": "br", "file": "example-006-br.html"},
  {"name": "cite", "file": "example-007-cite.html"},
  {"name": "code", "file": "example-008-code.html"},
  {"name": "data", "file": "example-009-data.html"},
  {"name": "dfn", "file": "example-010-dfn.html"},
  {"name": "em", "file": "example-011-em.html"},
  {"name": "i", "file": "example-012-i.html"},
  {"name": "kbd", "file": "example-013-kbd.html"},
  {"name": "mark", "file": "example-014-mark.html"},
  {"name": "q", "file": "example-015-q.html"},
  {"name": "rp", "file": "example-016-rp.html"},
  {"name": "rt", "file": "example-017-rt.html"},
  {"name": "ruby", "file": "example-018-ruby.html"},
  {"name": "s", "file": "example-019-s.html"},
  {"name": "samp", "file": "example-020-samp.html"},
  {"name": "small", "file": "example-021-small.html"},
  {"name": "span", "file": "example-022-span.html"},
  {"name": "strong", "file": "example-023-strong.html"},
  {"name": "sub", "file": "example-024-sub.html"},
  {"name": "sup", "file": "example-025-sup.html"},
  {"name": "time", "file": "example-026-time.html"},
  {"name": "u", "file": "example-027-u.html"},
  {"name": "var", "file": "example-028-var.html"},
  {"name": "wbr", "file": "example-029-wbr.html"},
  {"name": "address", "file": "example-030-address.html"},
  {"name": "article", "file": "example-031-article.html"},
  {"name": "aside", "file": "example-032-aside.html"},
  {"name": "footer", "file": "example-033-footer.html"},
  {"name": "header", "file": "example-034-header.html"},
  {"name": "h1", "file": "example-035-h1.html"},
  {"name": "h2", "file": "example-036-h2.html"},
  {"name": "h3", "file": "example-037-h3.html"},
  {"name": "h4", "file": "example-038-h4.html"},
  {"name": "h5", "file": "example-039-h5.html"},
  {"name": "h6", "file": "example-040-h6.html"},
  {"name": "hgroup", "file": "example-041-hgroup.html"},
  {"name": "main", "file": "example-042-main.html"},
  {"name": "nav", "file": "example-043-nav.html"},
  {"name": "section", "file": "example-044-section.html"},
  {"name": "search", "file": "example-045-search.html"},
  {"name": "blockquote", "file": "example-046-blockquote.html"},
  {"name": "dd", "file": "example-047-dd.html"},
  {"name": "div", "file": "example-048-div.html"},
  {"name": "dl", "file": "example-049-dl.html"},
  {"name": "dt", "file": "example-050-dt.html"},
  {"name": "figcaption", "file": "example-051-figcaption.html"},
  {"name": "figure", "file": "example-052-figure.html"},
  {"name": "hr", "file": "example-053-hr.html"},
  {"name": "li", "file": "example-054-li.html"},
  {"name": "menu", "file": "example-055-menu.html"},
  {"name": "ol", "file": "example-056-ol.html"},
  {"name": "p", "file": "example-057-p.html"},
  {"name": "pre", "file": "example-058-pre.html"},
  {"name": "ul", "file": "example-059-ul.html"},
  {"name": "area", "file": "example-060-area.html"},
  {"name": "audio", "file": "example-061-audio.html"},
  {"name": "img", "file": "example-062-img.html"},
  {"name": "map", "file": "example-063-map.html"},
  {"name": "track", "file": "example-064-track.html"},
  {"name": "video", "file": "example-065-video.html"},
  {"name": "embed", "file": "example-066-embed.html"},
  {"name": "iframe", "file": "example-068-iframe.html"},
  {"name": "object", "file": "example-069-object.html"},
  {"name": "picture", "file": "example-070-picture.html"},
  {"name": "source", "file": "example-071-source.html"},
  {"name": "svg", "file": "example-072-svg.html"},
  {"name": "math", "file": "example-073-math.html"},
  {"name": "canvas", "file": "example-074-canvas.html"},
  {"name": "noscript", "file": "example-075-noscript.html"},
  {"name": "script", "file": "example-076-script.html"},
  {"name": "del", "file": "example-077-del.html"},
  {"name": "ins", "file": "example-078-ins.html"},
  {"name": "caption", "file": "example-079-caption.html"},
  {"name": "col", "file": "example-080-col.html"},
  {"name": "colgroup", "file": "example-081-colgroup.html"},
  {"name": "table", "file": "example-082-table.html"},
  {"name": "tbody", "file": "example-083-tbody.html"},
  {"name": "td", "file": "example-084-td.html"},
  {"name": "tfoot", "file": "example-085-tfoot.html"},
  {"name": "th", "file": "example-086-th.html"},
  {"name": "thead", "file": "example-087-thead.html"},
  {"name": "tr", "file": "example-088-tr.html"},
  {"name": "button", "file": "example-089-button.html"},
  {"name": "datalist", "file": "example-090-datalist.html"},
  {"name": "fieldset", "file": "example-091-fieldset.html"},
  {"name": "form", "file": "example-092-form.html"},
  {"name": "input", "file": "example-093-input.html"},
  {"name": "label", "file": "example-094-label.html"},
  {"name": "legend", "file": "example-095-legend.html"},
  {"name": "meter", "file": "example-096-meter.html"},
  {"name": "optgroup", "file": "example-097-optgroup.html"},
  {"name": "option", "file": "example-098-option.html"},
  {"name": "output", "file": "example-099-output.html"},
  {"name": "progress", "file": "example-100-progress.html"},
  {"name": "select", "file": "example-101-select.html"},
  {"name": "selectedcontent", "file": "example-102-selectedcontent.html"},
  {"name": "textarea", "file": "example-103-textarea.html"},
  {"name": "details", "file": "example-104-details.html"},
  {"name": "dialog", "file": "example-105-dialog.html"},
  {"name": "summary", "file": "example-106-summary.html"}
]
